pass_at_k/__init__.py
pass_at_k-0.0.2.dist-info/METADATA
pass_at_k-0.0.2.dist-info/WHEEL
pass_at_k-0.0.2.dist-info/licenses/LICENSE
pass_at_k-0.0.2.dist-info/RECORD
