Metadata-Version: 2.3
Name: pass_at_k
Version: 0.0.2
Summary: A minimalistic Python library to evaluate the pass-at-k metric
Project-URL: Homepage, https://github.com/parker-research/pass-at-k
Project-URL: Issues, https://github.com/parker-research/pass-at-k/issues
Project-URL: Repository, https://github.com/parker-research/pass-at-k
Author: parker-research
License-Expression: Unlicense
License-File: LICENSE
Classifier: License :: OSI Approved :: The Unlicense (Unlicense)
Classifier: Operating System :: OS Independent
Classifier: Programming Language :: Python :: 3
Requires-Python: >=3.8
